paper_qa-2026.1.5.dist-info/licenses/LICENSE
paperqa/__init__.py
paperqa/_ldp_shims.py
paperqa/core.py
paperqa/docs.py
paperqa/llms.py
paperqa/paths.py
paperqa/prompts.py
paperqa/py.typed
paperqa/readers.py
paperqa/settings.py
paperqa/types.py
paperqa/utils.py
paperqa/version.py
paperqa/agents/__init__.py
paperqa/agents/env.py
paperqa/agents/helpers.py
paperqa/agents/main.py
paperqa/agents/models.py
paperqa/agents/search.py
paperqa/agents/tools.py
paperqa/clients/__init__.py
paperqa/clients/client_models.py
paperqa/clients/crossref.py
paperqa/clients/exceptions.py
paperqa/clients/journal_quality.py
paperqa/clients/openalex.py
paperqa/clients/retractions.py
paperqa/clients/semantic_scholar.py
paperqa/clients/unpaywall.py
paperqa/clients/client_data/journal_quality.csv
paperqa/configs/clinical_trials.json
paperqa/configs/contracrow.json
paperqa/configs/debug.json
paperqa/configs/fast.json
paperqa/configs/high_quality.json
paperqa/configs/openreview.json
paperqa/configs/search_only_clinical_trials.json
paperqa/configs/tier1_limits.json
paperqa/configs/tier2_limits.json
paperqa/configs/tier3_limits.json
paperqa/configs/tier4_limits.json
paperqa/configs/tier5_limits.json
paperqa/configs/wikicrow.json
paperqa/contrib/__init__.py
paperqa/contrib/openreview_paper_helper.py
paperqa/contrib/zotero.py
paperqa/sources/__init__.py
paperqa/sources/clinical_trials.py
paper_qa-2026.1.5.dist-info/METADATA
paper_qa-2026.1.5.dist-info/WHEEL
paper_qa-2026.1.5.dist-info/entry_points.txt
paper_qa-2026.1.5.dist-info/top_level.txt
paper_qa-2026.1.5.dist-info/RECORD
