Metadata-Version: 2.4
Name: paper-qa
Version: 2026.1.5
Summary: LLM Chain for answering questions from docs
Author-email: FutureHouse technical staff <hello@futurehouse.org>
Maintainer-email: James Braza <jamesbraza@gmail.com>, Michael Skarlinski <michael.skarlinski@gmail.com>, Andrew White <white.d.andrew@gmail.com>
License:                                  Apache License
Project-URL: issues, https://github.com/Future-House/paper-qa/issues
Project-URL: repository, https://github.com/Future-House/paper-qa
Keywords: question answering
Classifier: Intended Audience :: Developers
Classifier: License :: OSI Approved :: Apache Software License
Classifier: Operating System :: OS Independent
Classifier: Programming Language :: Python :: 3 :: Only
Classifier: Programming Language :: Python :: 3.11
Classifier: Programming Language :: Python :: 3.12
Classifier: Programming Language :: Python :: 3.13
Classifier: Programming Language :: Python
Classifier: Topic :: Scientific/Engineering :: Artificial Intelligence
Requires-Python: >=3.11
License-File: LICENSE
Requires-Dist: anyio
Requires-Dist: fhaviary[llm]>=0.27
Requires-Dist: fhlmi>=0.41.0
Requires-Dist: html2text
Requires-Dist: httpx
Requires-Dist: httpx-aiohttp
Requires-Dist: numpy
Requires-Dist: paper-qa-pypdf
Requires-Dist: pybtex
Requires-Dist: pydantic-settings
Requires-Dist: pydantic>=2.10.1,~=2.0
Requires-Dist: rich
Requires-Dist: setuptools
Requires-Dist: tantivy
Requires-Dist: tenacity
Requires-Dist: tiktoken>=0.4.0
Provides-Extra: dev
Requires-Dist: httpx-aiohttp>=0.1.11; extra == "dev"
Requires-Dist: ipykernel>=6.29; extra == "dev"
Requires-Dist: ipython>=8; extra == "dev"
Requires-Dist: litellm>=1.71; extra == "dev"
Requires-Dist: mypy>=1.19; extra == "dev"
Requires-Dist: paper-qa[docling,image,ldp,local,memory,nemotron,office,pymupdf,pypdf-media,qdrant,typing,zotero]; extra == "dev"
Requires-Dist: prek<0.2.15; extra == "dev"
Requires-Dist: pydantic~=2.11; extra == "dev"
Requires-Dist: pylint-per-file-ignores; extra == "dev"
Requires-Dist: pylint-pydantic; extra == "dev"
Requires-Dist: pytest-asyncio; extra == "dev"
Requires-Dist: pytest-recording; extra == "dev"
Requires-Dist: pytest-rerunfailures; extra == "dev"
Requires-Dist: pytest-subtests; extra == "dev"
Requires-Dist: pytest-sugar; extra == "dev"
Requires-Dist: pytest-timeout; extra == "dev"
Requires-Dist: pytest-timer[colorama]; extra == "dev"
Requires-Dist: pytest-xdist; extra == "dev"
Requires-Dist: pytest>=8; extra == "dev"
Requires-Dist: python-dotenv; extra == "dev"
Requires-Dist: refurb>=2; extra == "dev"
Requires-Dist: typeguard; extra == "dev"
Requires-Dist: vcrpy>=8; extra == "dev"
Provides-Extra: docling
Requires-Dist: paper-qa-docling; extra == "docling"
Provides-Extra: image
Requires-Dist: fhlmi[image]; extra == "image"
Provides-Extra: ldp
Requires-Dist: ldp<1,>=0.25.0; extra == "ldp"
Provides-Extra: local
Requires-Dist: sentence-transformers; extra == "local"
Provides-Extra: memory
Requires-Dist: paper-qa[ldp]; extra == "memory"
Requires-Dist: usearch>=2.16.4; extra == "memory"
Provides-Extra: nemotron
Requires-Dist: paper-qa-nemotron; extra == "nemotron"
Provides-Extra: office
Requires-Dist: unstructured[docx,pptx,xlsx]; extra == "office"
Provides-Extra: openreview
Requires-Dist: openreview-py; extra == "openreview"
Provides-Extra: pymupdf
Requires-Dist: paper-qa-pymupdf; extra == "pymupdf"
Provides-Extra: pypdf
Requires-Dist: paper-qa-pypdf; extra == "pypdf"
Provides-Extra: pypdf-enhanced
Requires-Dist: paper-qa-pypdf[enhanced]; extra == "pypdf-enhanced"
Provides-Extra: pypdf-media
Requires-Dist: paper-qa-pypdf[media]; extra == "pypdf-media"
Provides-Extra: qdrant
Requires-Dist: qdrant-client; extra == "qdrant"
Provides-Extra: typing
Requires-Dist: tantivy>=0.22.2; extra == "typing"
Requires-Dist: types-PyYAML; extra == "typing"
Requires-Dist: types-setuptools; extra == "typing"
Provides-Extra: zotero
Requires-Dist: paper-qa-pymupdf; extra == "zotero"
Requires-Dist: pyzotero; extra == "zotero"
Dynamic: license-file
